Workbook

Sheet Dashboard
D1: 📦 RETAIL INVENTORY ANALYTICS
A2: DASHBOARD📈
D3: Smarter Inventory • Better Decisions • Higher Profits
A5: SALES HISTORY | F5: TOTAL PRODUCTS 📥 | K5: TOTAL INVENTORY VALUE | P5: PRODUCTS AT RISK📉 | U5: A-CLASS PRODUCTS
F6: =COUNTA('Product Master'!A2:A21) -> 20 | K6: =SUM('Forecast & EOQ'!H2:H21) -> 638627.63 | P6: =COUNTIF('Forecast & EOQ'!W2:W21,"Yes") -> 2 | U6: =COUNTIF('Forecast & EOQ'!U2:U21,"A") -> 4
A8: PRODUCT MASTER
A11: FORECAST & EOQ
A18: CATEGORY ▾
A23: STOCK STATUS ▾

Sheet Sales History
A1: Product ID | B1: Product Name | C1: Category | D1: Jan | E1: Feb | F1: Mar | G1: Apr | H1: May | I1: Jun | J1: Jul | K1: Aug | L1: Sep | M1: Oct | N1: Nov | O1: Dec | P1: Total Units Sold | Q1: Avg Monthly Demand
A2: P1000 | B2: Wireless Earbuds | C2: Electronics Accessories | D2: 133 | E2: 155 | F2: 171 | G2: 155 | H2: 140 | I2: 134 | J2: 136 | K2: 119 | L2: 131 | M2: 114 | N2: 129 | O2: 147 | P2: =SUM(D2:O2) -> 1664 | Q2: =P2/12 -> 138.66667
A3: P1001 | B3: USB-C Charging Cable | C3: Home & Kitchen | D3: 109 | E3: 106 | F3: 102 | G3: 78 | H3: 73 | I3: 69 | J3: 63 | K3: 69 | L3: 93 | M3: 106 | N3: 108 | O3: 119 | P3: =SUM(D3:O3) -> 1095 | Q3: =P3/12 -> 91.25
A4: P1002 | B4: Bluetooth Speaker | C4: Apparel | D4: 72 | E4: 45 | F4: 47 | G4: 53 | H4: 50 | I4: 62 | J4: 76 | K4: 93 | L4: 92 | M4: 95 | N4: 94 | O4: 88 | P4: =SUM(D4:O4) -> 867 | Q4: =P4/12 -> 72.25
A5: P1003 | B5: Phone Stand | C5: Grocery | D5: 28 | E5: 34 | F5: 46 | G5: 51 | H5: 51 | I5: 53 | J5: 52 | K5: 51 | L5: 48 | M5: 40 | N5: 41 | O5: 40 | P5: =SUM(D5:O5) -> 535 | Q5: =P5/12 -> 44.583333
A6: P1004 | B6: Non-Stick Frying Pan | C6: Beauty & Personal Care | D6: 54 | E6: 61 | F6: 61 | G6: 52 | H6: 44 | I6: 38 | J6: 43 | K6: 44 | L6: 46 | M6: 58 | N6: 65 | O6: 74 | P6: =SUM(D6:O6) -> 640 | Q6: =P6/12 -> 53.333333
A7: P1005 | B7: Ceramic Mug Set | C7: Electronics Accessories | D7: 91 | E7: 78 | F7: 82 | G7: 72 | H7: 56 | I7: 60 | J7: 69 | K7: 66 | L7: 78 | M7: 104 | N7: 115 | O7: 138 | P7: =SUM(D7:O7) -> 1009 | Q7: =P7/12 -> 84.083333
A8: P1006 | B8: Electric Kettle | C8: Home & Kitchen | D8: 107 | E8: 112 | F8: 106 | G8: 120 | H8: 136 | I8: 126 | J8: 101 | K8: 95 | L8: 102 | M8: 74 | N8: 75 | O8: 85 | P8: =SUM(D8:O8) -> 1239 | Q8: =P8/12 -> 103.25
A9: P1007 | B9: Cutlery Set | C9: Apparel | D9: 54 | E9: 54 | F9: 74 | G9: 79 | H9: 81 | I9: 78 | J9: 73 | K9: 66 | L9: 55 | M9: 62 | N9: 70 | O9: 70 | P9: =SUM(D9:O9) -> 816 | Q9: =P9/12 -> 68
A10: P1008 | B10: Cotton T-Shirt | C10: Grocery | D10: 107 | E10: 110 | F10: 109 | G10: 114 | H10: 142 | I10: 166 | J10: 145 | K10: 135 | L10: 157 | M10: 124 | N10: 115 | O10: 122 | P10: =SUM(D10:O10) -> 1546 | Q10: =P10/12 -> 128.83333
A11: P1009 | B11: Denim Jeans | C11: Beauty & Personal Care | D11: 27 | E11: 28 | F11: 35 | G11: 31 | H11: 31 | I11: 33 | J11: 32 | K11: 33 | L11: 26 | M11: 30 | N11: 28 | O11: 31 | P11: =SUM(D11:O11) -> 365 | Q11: =P11/12 -> 30.416667
A12: P1010 | B12: Running Shoes | C12: Electronics Accessories | D12: 207 | E12: 182 | F12: 180 | G12: 157 | H12: 158 | I12: 114 | J12: 98 | K12: 98 | L12: 114 | M12: 126 | N12: 155 | O12: 182 | P12: =SUM(D12:O12) -> 1771 | Q12: =P12/12 -> 147.58333
A13: P1011 | B13: Woolen Scarf | C13: Home & Kitchen | D13: 154 | E13: 184 | F13: 153 | G13: 180 | H13: 138 | I13: 143 | J13: 126 | K13: 113 | L13: 128 | M13: 132 | N13: 129 | O13: 123 | P13: =SUM(D13:O13) -> 1703 | Q13: =P13/12 -> 141.91667
... A21: P1019 | B21: Lip Balm Pack | C21: Beauty & Personal Care | D21: 38 | E21: 50 | F21: 48 | G21: 48 | H21: 43 | I21: 42 | J21: 35 | K21: 33 | L21: 27 | M21: 35 | N21: 27 | O21: 29 | P21: =SUM(D21:O21) -> 455 | Q21: =P21/12 -> 37.916667

Sheet Product Master
A1: Product ID | B1: Product Name | C1: Category | D1: Supplier | E1: Cost Price ($) | F1: Selling Price ($) | G1: Current Stock (Units) | H1: Lead Time (Days) | I1: Ordering Cost ($/order) | J1: Holding Cost (% per year)
A2: ='Sales History'!A2 -> P1000 | B2: ='Sales History'!B2 -> Wireless Earbuds | C2: ='Sales History'!C2 -> Electronics Accessories | D2: Nova Supplies Co. | E2: 24.35 | F2: 45.06 | G2: 278 | H2: 14 | I2: 28.21 | J2: 0.26
A3: ='Sales History'!A3 -> P1001 | B3: ='Sales History'!B3 -> USB-C Charging Cable | C3: ='Sales History'!C3 -> Home & Kitchen | D3: Prime Distributors | E3: 57.19 | F3: 81.53 | G3: 49 | H3: 5 | I3: 15.63 | J3: 0.24
A4: ='Sales History'!A4 -> P1002 | B4: ='Sales History'!B4 -> Bluetooth Speaker | C4: ='Sales History'!C4 -> Apparel | D4: Unity Wholesale | E4: 44.72 | F4: 69.89 | G4: 220 | H4: 21 | I4: 23.95 | J4: 0.16
A5: ='Sales History'!A5 -> P1003 | B5: ='Sales History'!B5 -> Phone Stand | C5: ='Sales History'!C5 -> Grocery | D5: Global Traders Ltd. | E5: 37.12 | F5: 60.5 | G5: 95 | H5: 21 | I5: 47.01 | J5: 0.16
A6: ='Sales History'!A6 -> P1004 | B6: ='Sales History'!B6 -> Non-Stick Frying Pan | C6: ='Sales History'!C6 -> Beauty & Personal Care | D6: Metro Logistics | E6: 11.89 | F6: 20.34 | G6: 64 | H6: 7 | I6: 50.56 | J6: 0.13
A7: ='Sales History'!A7 -> P1005 | B7: ='Sales History'!B7 -> Ceramic Mug Set | C7: ='Sales History'!C7 -> Electronics Accessories | D7: Nova Supplies Co. | E7: 11.89 | F7: 23.86 | G7: 374 | H7: 21 | I7: 42.27 | J7: 0.23
A8: ='Sales History'!A8 -> P1006 | B8: ='Sales History'!B8 -> Electric Kettle | C8: ='Sales History'!C8 -> Home & Kitchen | D8: Prime Distributors | E8: 6.31 | F8: 9.34 | G8: 16 | H8: 7 | I8: 56.68 | J8: 0.14
A9: ='Sales History'!A9 -> P1007 | B9: ='Sales History'!B9 -> Cutlery Set | C9: ='Sales History'!C9 -> Apparel | D9: Unity Wholesale | E9: 52.37 | F9: 92.32 | G9: 68 | H9: 5 | I9: 44.3 | J9: 0.19
A10: ='Sales History'!A10 -> P1008 | B10: ='Sales History'!B10 -> Cotton T-Shirt | C10: ='Sales History'!C10 -> Grocery | D10: Global Traders Ltd. | E10: 37.26 | F10: 68.3 | G10: 120 | H10: 14 | I10: 56.17 | J10: 0.15
A11: ='Sales History'!A11 -> P1009 | B11: ='Sales History'!B11 -> Denim Jeans | C11: ='Sales History'!C11 -> Beauty & Personal Care | D11: Metro Logistics | E11: 43.36 | F11: 58.18 | G11: 274 | H11: 14 | I11: 53.25 | J11: 0.26
A12: ='Sales History'!A12 -> P1010 | B12: ='Sales History'!B12 -> Running Shoes | C12: ='Sales History'!C12 -> Electronics Accessories | D12: Nova Supplies Co. | E12: 4.17 | F12: 7.7 | G12: 324 | H12: 14 | I12: 35.23 | J12: 0.2
A13: ='Sales History'!A13 -> P1011 | B13: ='Sales History'!B13 -> Woolen Scarf | C13: ='Sales History'!C13 -> Home & Kitchen | D13: Prime Distributors | E13: 58.28 | F13: 84.71 | G13: 205 | H13: 21 | I13: 19.29 | J13: 0.21
... A21: ='Sales History'!A21 -> P1019 | B21: ='Sales History'!B21 -> Lip Balm Pack | C21: ='Sales History'!C21 -> Beauty & Personal Care | D21: Metro Logistics | E21: 19.6 | F21: 33.24 | G21: 285 | H21: 14 | I21: 58.73 | J21: 0.23

Sheet Forecast & EOQ
A1: Product ID | B1: Product Name | C1: Avg Monthly Demand | D1: Forecast Next Month | E1: Category | F1: Annual Demand | G1: Cost Price ($) | H1: Annual Usage Value ($) | I1: Current Stock | J1: Lead Time (Days) | K1: Ordering Cost ($) | L1: Holding Cost (%) | M1: Daily Demand | N1: Safety Stock | O1: Reorder Point | P1: EOQ (Units) | Q1: Days of Stock Remaining | R1: Stock Status | S1: Value Rank | T1: Percentile | U1: ABC Class | V1: Adj. Reorder Point (What-If) | W1: At Risk? (What-If)
A2: ='Sales History'!A2 -> P1000 | B2: ='Sales History'!B2 -> Wireless Earbuds | C2: ='Sales History'!Q2 -> 138.66667 | D2: =_xlfn.FORECAST.LINEAR(13,'Sales History'!D2:O2,{1,2,3,4,5,6,7,8,9,10,11,12}) -> 123.66667 | E2: ='Sales History'!C2 -> Electronics Accessories | F2: =C2*12 -> 1664 | G2: =INDEX('Product Master'!$E$2:$E$21,MATCH(A2,'Product Master'!$A$2:$A$21,0)) -> 24.35 | H2: =F2*G2 -> 40518.4 | I2: =INDEX('Product Master'!$G$2:$G$21,MATCH(A2,'Product Master'!$A$2:$A$21,0)) -> 278 | J2: =INDEX('Product Master'!$H$2:$H$21,MATCH(A2,'Product Master'!$A$2:$A$21,0)) -> 14 | K2: =INDEX('Product Master'!$I$2:$I$21,MATCH(A2,'Product Master'!$A$2:$A$21,0)) -> 28.21 | L2: =INDEX('Product Master'!$J$2:$J$21,MATCH(A2,'Product Master'!$A$2:$A$21,0)) -> 0.26 | M2: =F2/365 -> 4.5589041 | N2: =M2*J2*0.2 -> 12.764932 | O2: =M2*J2+N2 -> 76.589589 | P2: =IFERROR(SQRT(2*F2*K2/(G2*L2)),0) -> 121.77469 | Q2: =IFERROR(I2/M2,0) -> 60.979567 | R2: =IF(I2<=O2,"Reorder Now",IF(Q2<30,"Monitor","Healthy")) -> Healthy | S2: =RANK(H2,$H$2:$H$21,0) -> 8 | T2: =S2/COUNT($H$2:$H$21) -> 0.4 | U2: =IF(T2<=0.2,"A",IF(T2<=0.5,"B","C")) -> B | V2: =M2*14+N2 -> 76.589589 | W2: =IF(I2<=V2,"Yes","No") -> No
A3: ='Sales History'!A3 -> P1001 | B3: ='Sales History'!B3 -> USB-C Charging Cable | C3: ='Sales History'!Q3 -> 91.25 | D3: =_xlfn.FORECAST.LINEAR(13,'Sales History'!D3:O3,{1,2,3,4,5,6,7,8,9,10,11,12}) -> 96.090909 | E3: ='Sales History'!C3 -> Home & Kitchen | F3: =C3*12 -> 1095 | G3: =INDEX('Product Master'!$E$2:$E$21,MATCH(A3,'Product Master'!$A$2:$A$21,0)) -> 57.19 | H3: =F3*G3 -> 62623.05 | I3: =INDEX('Product Master'!$G$2:$G$21,MATCH(A3,'Product Master'!$A$2:$A$21,0)) -> 49 | J3: =INDEX('Product Master'!$H$2:$H$21,MATCH(A3,'Product Master'!$A$2:$A$21,0)) -> 5 | K3: =INDEX('Product Master'!$I$2:$I$21,MATCH(A3,'Product Master'!$A$2:$A$21,0)) -> 15.63 | L3: =INDEX('Product Master'!$J$2:$J$21,MATCH(A3,'Product Master'!$A$2:$A$21,0)) -> 0.24 | M3: =F3/365 -> 3 | N3: =M3*J3*0.2 -> 3 | O3: =M3*J3+N3 -> 18 | P3: =IFERROR(SQRT(2*F3*K3/(G3*L3)),0) -> 49.938544 | Q3: =IFERROR(I3/M3,0) -> 16.333333 | R3: =IF(I3<=O3,"Reorder Now",IF(Q3<30,"Monitor","Healthy")) -> Monitor | S3: =RANK(H3,$H$2:$H$21,0) -> 2 | T3: =S3/COUNT($H$2:$H$21) -> 0.1 | U3: =IF(T3<=0.2,"A",IF(T3<=0.5,"B","C")) -> A | V3: =M3*14+N3 -> 45 | W3: =IF(I3<=V3,"Yes","No") -> No
A4: ='Sales History'!A4 -> P1002 | B4: ='Sales History'!B4 -> Bluetooth Speaker | C4: ='Sales History'!Q4 -> 72.25 | D4: =_xlfn.FORECAST.LINEAR(13,'Sales History'!D4:O4,{1,2,3,4,5,6,7,8,9,10,11,12}) -> 101.59091 | E4: ='Sales History'!C4 -> Apparel | F4: =C4*12 -> 867 | G4: =INDEX('Product Master'!$E$2:$E$21,MATCH(A4,'Product Master'!$A$2:$A$21,0)) -> 44.72 | H4: =F4*G4 -> 38772.24 | I4: =INDEX('Product Master'!$G$2:$G$21,MATCH(A4,'Product Master'!$A$2:$A$21,0)) -> 220 | J4: =INDEX('Product Master'!$H$2:$H$21,MATCH(A4,'Product Master'!$A$2:$A$21,0)) -> 21 | K4: =INDEX('Product Master'!$I$2:$I$21,MATCH(A4,'Product Master'!$A$2:$A$21,0)) -> 23.95 | L4: =INDEX('Product Master'!$J$2:$J$21,MATCH(A4,'Product Master'!$A$2:$A$21,0)) -> 0.16 | M4: =F4/365 -> 2.3753425 | N4: =M4*J4*0.2 -> 9.9764384 | O4: =M4*J4+N4 -> 59.85863 | P4: =IFERROR(SQRT(2*F4*K4/(G4*L4)),0) -> 76.184464 | Q4: =IFERROR(I4/M4,0) -> 92.618224 | R4: =IF(I4<=O4,"Reorder Now",IF(Q4<30,"Monitor","Healthy")) -> Healthy | S4: =RANK(H4,$H$2:$H$21,0) -> 9 | T4: =S4/COUNT($H$2:$H$21) -> 0.45 | U4: =IF(T4<=0.2,"A",IF(T4<=0.5,"B","C")) -> B | V4: =M4*14+N4 -> 43.231233 | W4: =IF(I4<=V4,"Yes","No") -> No
A5: ='Sales History'!A5 -> P1003 | B5: ='Sales History'!B5 -> Phone Stand | C5: ='Sales History'!Q5 -> 44.583333 | D5: =_xlfn.FORECAST.LINEAR(13,'Sales History'!D5:O5,{1,2,3,4,5,6,7,8,9,10,11,12}) -> 47.69697 | E5: ='Sales History'!C5 -> Grocery | F5: =C5*12 -> 535 | G5: =INDEX('Product Master'!$E$2:$E$21,MATCH(A5,'Product Master'!$A$2:$A$21,0)) -> 37.12 | H5: =F5*G5 -> 19859.2 | I5: =INDEX('Product Master'!$G$2:$G$21,MATCH(A5,'Product Master'!$A$2:$A$21,0)) -> 95 | J5: =INDEX('Product Master'!$H$2:$H$21,MATCH(A5,'Product Master'!$A$2:$A$21,0)) -> 21 | K5: =INDEX('Product Master'!$I$2:$I$21,MATCH(A5,'Product Master'!$A$2:$A$21,0)) -> 47.01 | L5: =INDEX('Product Master'!$J$2:$J$21,MATCH(A5,'Product Master'!$A$2:$A$21,0)) -> 0.16 | M5: =F5/365 -> 1.4657534 | N5: =M5*J5*0.2 -> 6.1561644 | O5: =M5*J5+N5 -> 36.936986 | P5: =IFERROR(SQRT(2*F5*K5/(G5*L5)),0) -> 92.028647 | Q5: =IFERROR(I5/M5,0) -> 64.813084 | R5: =IF(I5<=O5,"Reorder Now",IF(Q5<30,"Monitor","Healthy")) -> Healthy | S5: =RANK(H5,$H$2:$H$21,0) -> 11 | T5: =S5/COUNT($H$2:$H$21) -> 0.55 | U5: =IF(T5<=0.2,"A",IF(T5<=0.5,"B","C")) -> C | V5: =M5*14+N5 -> 26.676712 | W5: =IF(I5<=V5,"Yes","No") -> No | Z5: ABC Class | AA5: Products
A6: ='Sales History'!A6 -> P1004 | B6: ='Sales History'!B6 -> Non-Stick Frying Pan | C6: ='Sales History'!Q6 -> 53.333333 | D6: =_xlfn.FORECAST.LINEAR(13,'Sales History'!D6:O6,{1,2,3,4,5,6,7,8,9,10,11,12}) -> 58.106061 | E6: ='Sales History'!C6 -> Beauty & Personal Care | F6: =C6*12 -> 640 | G6: =INDEX('Product Master'!$E$2:$E$21,MATCH(A6,'Product Master'!$A$2:$A$21,0)) -> 11.89 | H6: =F6*G6 -> 7609.6 | I6: =INDEX('Product Master'!$G$2:$G$21,MATCH(A6,'Product Master'!$A$2:$A$21,0)) -> 64 | J6: =INDEX('Product Master'!$H$2:$H$21,MATCH(A6,'Product Master'!$A$2:$A$21,0)) -> 7 | K6: =INDEX('Product Master'!$I$2:$I$21,MATCH(A6,'Product Master'!$A$2:$A$21,0)) -> 50.56 | L6: =INDEX('Product Master'!$J$2:$J$21,MATCH(A6,'Product Master'!$A$2:$A$21,0)) -> 0.13 | M6: =F6/365 -> 1.7534247 | N6: =M6*J6*0.2 -> 2.4547945 | O6: =M6*J6+N6 -> 14.728767 | P6: =IFERROR(SQRT(2*F6*K6/(G6*L6)),0) -> 204.61898 | Q6: =IFERROR(I6/M6,0) -> 36.5 | R6: =IF(I6<=O6,"Reorder Now",IF(Q6<30,"Monitor","Healthy")) -> Healthy | S6: =RANK(H6,$H$2:$H$21,0) -> 19 | T6: =S6/COUNT($H$2:$H$21) -> 0.95 | U6: =IF(T6<=0.2,"A",IF(T6<=0.5,"B","C")) -> C | V6: =M6*14+N6 -> 27.00274 | W6: =IF(I6<=V6,"Yes","No") -> No | Z6: A Class | AA6: =COUNTIF($U$2:$U$21,"A") -> 4 | AC6: Product Name | AD6: Inventory Value
A7: ='Sales History'!A7 -> P1005 | B7: ='Sales History'!B7 -> Ceramic Mug Set | C7: ='Sales History'!Q7 -> 84.083333 | D7: =_xlfn.FORECAST.LINEAR(13,'Sales History'!D7:O7,{1,2,3,4,5,6,7,8,9,10,11,12}) -> 108.4697 | E7: ='Sales History'!C7 -> Electronics Accessories | F7: =C7*12 -> 1009 | G7: =INDEX('Product Master'!$E$2:$E$21,MATCH(A7,'Product Master'!$A$2:$A$21,0)) -> 11.89 | H7: =F7*G7 -> 11997.01 | I7: =INDEX('Product Master'!$G$2:$G$21,MATCH(A7,'Product Master'!$A$2:$A$21,0)) -> 374 | J7: =INDEX('Product Master'!$H$2:$H$21,MATCH(A7,'Product Master'!$A$2:$A$21,0)) -> 21 | K7: =INDEX('Product Master'!$I$2:$I$21,MATCH(A7,'Product Master'!$A$2:$A$21,0)) -> 42.27 | L7: =INDEX('Product Master'!$J$2:$J$21,MATCH(A7,'Product Master'!$A$2:$A$21,0)) -> 0.23 | M7: =F7/365 -> 2.7643836 | N7: =M7*J7*0.2 -> 11.610411 | O7: =M7*J7+N7 -> 69.662466 | P7: =IFERROR(SQRT(2*F7*K7/(G7*L7)),0) -> 176.61267 | Q7: =IFERROR(I7/M7,0) -> 135.29237 | R7: =IF(I7<=O7,"Reorder Now",IF(Q7<30,"Monitor","Healthy")) -> Healthy | S7: =RANK(H7,$H$2:$H$21,0) -> 15 | T7: =S7/COUNT($H$2:$H$21) -> 0.75 | U7: =IF(T7<=0.2,"A",IF(T7<=0.5,"B","C")) -> C | V7: =M7*14+N7 -> 50.311781 | W7: =IF(I7<=V7,"Yes","No") -> No | Z7: B Class | AA7: =COUNTIF($U$2:$U$21,"B") -> 6 | AC7: =INDEX($B$2:$B$21,MATCH(AD7,$H$2:$H$21,0)) -> Woolen Scarf | AD7: =LARGE($H$2:$H$21,ROW(A1)) -> 99250.84
A8: ='Sales History'!A8 -> P1006 | B8: ='Sales History'!B8 -> Electric Kettle | C8: ='Sales History'!Q8 -> 103.25 | D8: =_xlfn.FORECAST.LINEAR(13,'Sales History'!D8:O8,{1,2,3,4,5,6,7,8,9,10,11,12}) -> 79.681818 | E8: ='Sales History'!C8 -> Home & Kitchen | F8: =C8*12 -> 1239 | G8: =INDEX('Product Master'!$E$2:$E$21,MATCH(A8,'Product Master'!$A$2:$A$21,0)) -> 6.31 | H8: =F8*G8 -> 7818.09 | I8: =INDEX('Product Master'!$G$2:$G$21,MATCH(A8,'Product Master'!$A$2:$A$21,0)) -> 16 | J8: =INDEX('Product Master'!$H$2:$H$21,MATCH(A8,'Product Master'!$A$2:$A$21,0)) -> 7 | K8: =INDEX('Product Master'!$I$2:$I$21,MATCH(A8,'Product Master'!$A$2:$A$21,0)) -> 56.68 | L8: =INDEX('Product Master'!$J$2:$J$21,MATCH(A8,'Product Master'!$A$2:$A$21,0)) -> 0.14 | M8: =F8/365 -> 3.3945205 | N8: =M8*J8*0.2 -> 4.7523288 | O8: =M8*J8+N8 -> 28.513973 | P8: =IFERROR(SQRT(2*F8*K8/(G8*L8)),0) -> 398.73731 | Q8: =IFERROR(I8/M8,0) -> 4.7134786 | R8: =IF(I8<=O8,"Reorder Now",IF(Q8<30,"Monitor","Healthy")) -> Reorder Now | S8: =RANK(H8,$H$2:$H$21,0) -> 18 | T8: =S8/COUNT($H$2:$H$21) -> 0.9 | U8: =IF(T8<=0.2,"A",IF(T8<=0.5,"B","C")) -> C | V8: =M8*14+N8 -> 52.275616 | W8: =IF(I8<=V8,"Yes","No") -> Yes | Z8: C Class | AA8: =COUNTIF($U$2:$U$21,"C") -> 10 | AC8: =INDEX($B$2:$B$21,MATCH(AD8,$H$2:$H$21,0)) -> USB-C Charging Cable | AD8: =LARGE($H$2:$H$21,ROW(A2)) -> 62623.05
A9: ='Sales History'!A9 -> P1007 | B9: ='Sales History'!B9 -> Cutlery Set | C9: ='Sales History'!Q9 -> 68 | D9: =_xlfn.FORECAST.LINEAR(13,'Sales History'!D9:O9,{1,2,3,4,5,6,7,8,9,10,11,12}) -> 69.5 | E9: ='Sales History'!C9 -> Apparel | F9: =C9*12 -> 816 | G9: =INDEX('Product Master'!$E$2:$E$21,MATCH(A9,'Product Master'!$A$2:$A$21,0)) -> 52.37 | H9: =F9*G9 -> 42733.92 | I9: =INDEX('Product Master'!$G$2:$G$21,MATCH(A9,'Product Master'!$A$2:$A$21,0)) -> 68 | J9: =INDEX('Product Master'!$H$2:$H$21,MATCH(A9,'Product Master'!$A$2:$A$21,0)) -> 5 | K9: =INDEX('Product Master'!$I$2:$I$21,MATCH(A9,'Product Master'!$A$2:$A$21,0)) -> 44.3 | L9: =INDEX('Product Master'!$J$2:$J$21,MATCH(A9,'Product Master'!$A$2:$A$21,0)) -> 0.19 | M9: =F9/365 -> 2.2356164 | N9: =M9*J9*0.2 -> 2.2356164 | O9: =M9*J9+N9 -> 13.413699 | P9: =IFERROR(SQRT(2*F9*K9/(G9*L9)),0) -> 85.240081 | Q9: =IFERROR(I9/M9,0) -> 30.416667 | R9: =IF(I9<=O9,"Reorder Now",IF(Q9<30,"Monitor","Healthy")) -> Healthy | S9: =RANK(H9,$H$2:$H$21,0) -> 6 | T9: =S9/COUNT($H$2:$H$21) -> 0.3 | U9: =IF(T9<=0.2,"A",IF(T9<=0.5,"B","C")) -> B | V9: =M9*14+N9 -> 33.534247 | W9: =IF(I9<=V9,"Yes","No") -> No | AC9: =INDEX($B$2:$B$21,MATCH(AD9,$H$2:$H$21,0)) -> Basmati Rice 5kg | AD9: =LARGE($H$2:$H$21,ROW(A3)) -> 62457.1
A10: ='Sales History'!A10 -> P1008 | B10: ='Sales History'!B10 -> Cotton T-Shirt | C10: ='Sales History'!Q10 -> 128.83333 | D10: =_xlfn.FORECAST.LINEAR(13,'Sales History'!D10:O10,{1,2,3,4,5,6,7,8,9,10,11,12}) -> 139.92424 | E10: ='Sales History'!C10 -> Grocery | F10: =C10*12 -> 1546 | G10: =INDEX('Product Master'!$E$2:$E$21,MATCH(A10,'Product Master'!$A$2:$A$21,0)) -> 37.26 | H10: =F10*G10 -> 57603.96 | I10: =INDEX('Product Master'!$G$2:$G$21,MATCH(A10,'Product Master'!$A$2:$A$21,0)) -> 120 | J10: =INDEX('Product Master'!$H$2:$H$21,MATCH(A10,'Product Master'!$A$2:$A$21,0)) -> 14 | K10: =INDEX('Product Master'!$I$2:$I$21,MATCH(A10,'Product Master'!$A$2:$A$21,0)) -> 56.17 | L10: =INDEX('Product Master'!$J$2:$J$21,MATCH(A10,'Product Master'!$A$2:$A$21,0)) -> 0.15 | M10: =F10/365 -> 4.2356164 | N10: =M10*J10*0.2 -> 11.859726 | O10: =M10*J10+N10 -> 71.158356 | P10: =IFERROR(SQRT(2*F10*K10/(G10*L10)),0) -> 176.28075 | Q10: =IFERROR(I10/M10,0) -> 28.331177 | R10: =IF(I10<=O10,"Reorder Now",IF(Q10<30,"Monitor","Healthy")) -> Monitor | S10: =RANK(H10,$H$2:$H$21,0) -> 4 | T10: =S10/COUNT($H$2:$H$21) -> 0.2 | U10: =IF(T10<=0.2,"A",IF(T10<=0.5,"B","C")) -> A | V10: =M10*14+N10 -> 71.158356 | W10: =IF(I10<=V10,"Yes","No") -> No | AC10: =INDEX($B$2:$B$21,MATCH(AD10,$H$2:$H$21,0)) -> Cotton T-Shirt | AD10: =LARGE($H$2:$H$21,ROW(A4)) -> 57603.96
A11: ='Sales History'!A11 -> P1009 | B11: ='Sales History'!B11 -> Denim Jeans | C11: ='Sales History'!Q11 -> 30.416667 | D11: =_xlfn.FORECAST.LINEAR(13,'Sales History'!D11:O11,{1,2,3,4,5,6,7,8,9,10,11,12}) -> 30.166667 | E11: ='Sales History'!C11 -> Beauty & Personal Care | F11: =C11*12 -> 365 | G11: =INDEX('Product Master'!$E$2:$E$21,MATCH(A11,'Product Master'!$A$2:$A$21,0)) -> 43.36 | H11: =F11*G11 -> 15826.4 | I11: =INDEX('Product Master'!$G$2:$G$21,MATCH(A11,'Product Master'!$A$2:$A$21,0)) -> 274 | J11: =INDEX('Product Master'!$H$2:$H$21,MATCH(A11,'Product Master'!$A$2:$A$21,0)) -> 14 | K11: =INDEX('Product Master'!$I$2:$I$21,MATCH(A11,'Product Master'!$A$2:$A$21,0)) -> 53.25 | L11: =INDEX('Product Master'!$J$2:$J$21,MATCH(A11,'Product Master'!$A$2:$A$21,0)) -> 0.26 | M11: =F11/365 -> 1 | N11: =M11*J11*0.2 -> 2.8 | O11: =M11*J11+N11 -> 16.8 | P11: =IFERROR(SQRT(2*F11*K11/(G11*L11)),0) -> 58.720524 | Q11: =IFERROR(I11/M11,0) -> 274 | R11: =IF(I11<=O11,"Reorder Now",IF(Q11<30,"Monitor","Healthy")) -> Healthy | S11: =RANK(H11,$H$2:$H$21,0) -> 12 | T11: =S11/COUNT($H$2:$H$21) -> 0.6 | U11: =IF(T11<=0.2,"A",IF(T11<=0.5,"B","C")) -> C | V11: =M11*14+N11 -> 16.8 | W11: =IF(I11<=V11,"Yes","No") -> No | AC11: =INDEX($B$2:$B$21,MATCH(AD11,$H$2:$H$21,0)) -> Shampoo 400ml | AD11: =LARGE($H$2:$H$21,ROW(A5)) -> 50385.21
A12: ='Sales History'!A12 -> P1010 | B12: ='Sales History'!B12 -> Running Shoes | C12: ='Sales History'!Q12 -> 147.58333 | D12: =_xlfn.FORECAST.LINEAR(13,'Sales History'!D12:O12,{1,2,3,4,5,6,7,8,9,10,11,12}) -> 117.87879 | E12: ='Sales History'!C12 -> Electronics Accessories | F12: =C12*12 -> 1771 | G12: =INDEX('Product Master'!$E$2:$E$21,MATCH(A12,'Product Master'!$A$2:$A$21,0)) -> 4.17 | H12: =F12*G12 -> 7385.07 | I12: =INDEX('Product Master'!$G$2:$G$21,MATCH(A12,'Product Master'!$A$2:$A$21,0)) -> 324 | J12: =INDEX('Product Master'!$H$2:$H$21,MATCH(A12,'Product Master'!$A$2:$A$21,0)) -> 14 | K12: =INDEX('Product Master'!$I$2:$I$21,MATCH(A12,'Product Master'!$A$2:$A$21,0)) -> 35.23 | L12: =INDEX('Product Master'!$J$2:$J$21,MATCH(A12,'Product Master'!$A$2:$A$21,0)) -> 0.2 | M12: =F12/365 -> 4.8520548 | N12: =M12*J12*0.2 -> 13.585753 | O12: =M12*J12+N12 -> 81.514521 | P12: =IFERROR(SQRT(2*F12*K12/(G12*L12)),0) -> 386.80989 | Q12: =IFERROR(I12/M12,0) -> 66.775833 | R12: =IF(I12<=O12,"Reorder Now",IF(Q12<30,"Monitor","Healthy")) -> Healthy | S12: =RANK(H12,$H$2:$H$21,0) -> 20 | T12: =S12/COUNT($H$2:$H$21) -> 1 | U12: =IF(T12<=0.2,"A",IF(T12<=0.5,"B","C")) -> C | V12: =M12*14+N12 -> 81.514521 | W12: =IF(I12<=V12,"Yes","No") -> No | Z12: Stock Status | AA12: Products
A13: ='Sales History'!A13 -> P1011 | B13: ='Sales History'!B13 -> Woolen Scarf | C13: ='Sales History'!Q13 -> 141.91667 | D13: =_xlfn.FORECAST.LINEAR(13,'Sales History'!D13:O13,{1,2,3,4,5,6,7,8,9,10,11,12}) -> 111.57576 | E13: ='Sales History'!C13 -> Home & Kitchen | F13: =C13*12 -> 1703 | G13: =INDEX('Product Master'!$E$2:$E$21,MATCH(A13,'Product Master'!$A$2:$A$21,0)) -> 58.28 | H13: =F13*G13 -> 99250.84 | I13: =INDEX('Product Master'!$G$2:$G$21,MATCH(A13,'Product Master'!$A$2:$A$21,0)) -> 205 | J13: =INDEX('Product Master'!$H$2:$H$21,MATCH(A13,'Product Master'!$A$2:$A$21,0)) -> 21 | K13: =INDEX('Product Master'!$I$2:$I$21,MATCH(A13,'Product Master'!$A$2:$A$21,0)) -> 19.29 | L13: =INDEX('Product Master'!$J$2:$J$21,MATCH(A13,'Product Master'!$A$2:$A$21,0)) -> 0.21 | M13: =F13/365 -> 4.6657534 | N13: =M13*J13*0.2 -> 19.596164 | O13: =M13*J13+N13 -> 117.57699 | P13: =IFERROR(SQRT(2*F13*K13/(G13*L13)),0) -> 73.26879 | Q13: =IFERROR(I13/M13,0) -> 43.93717 | R13: =IF(I13<=O13,"Reorder Now",IF(Q13<30,"Monitor","Healthy")) -> Healthy | S13: =RANK(H13,$H$2:$H$21,0) -> 1 | T13: =S13/COUNT($H$2:$H$21) -> 0.05 | U13: =IF(T13<=0.2,"A",IF(T13<=0.5,"B","C")) -> A | V13: =M13*14+N13 -> 84.916712 | W13: =IF(I13<=V13,"Yes","No") -> No | Z13: Healthy | AA13: =COUNTIF($R$2:$R$21,"Healthy") -> 16
A14: ='Sales History'!A14 -> P1012 | B14: ='Sales History'!B14 -> Basmati Rice 5kg | C14: ='Sales History'!Q14 -> 103.16667 | D14: =_xlfn.FORECAST.LINEAR(13,'Sales History'!D14:O14,{1,2,3,4,5,6,7,8,9,10,11,12}) -> 72.848485 | E14: ='Sales History'!C14 -> Apparel | F14: =C14*12 -> 1238 | G14: =INDEX('Product Master'!$E$2:$E$21,MATCH(A14,'Product Master'!$A$2:$A$21,0)) -> 50.45 | H14: =F14*G14 -> 62457.1 | I14: =INDEX('Product Master'!$G$2:$G$21,MATCH(A14,'Product Master'!$A$2:$A$21,0)) -> 232 | J14: =INDEX('Product Master'!$H$2:$H$21,MATCH(A14,'Product Master'!$A$2:$A$21,0)) -> 5 | K14: =INDEX('Product Master'!$I$2:$I$21,MATCH(A14,'Product Master'!$A$2:$A$21,0)) -> 31.69 | L14: =INDEX('Product Master'!$J$2:$J$21,MATCH(A14,'Product Master'!$A$2:$A$21,0)) -> 0.23 | M14: =F14/365 -> 3.3917808 | N14: =M14*J14*0.2 -> 3.3917808 | O14: =M14*J14+N14 -> 20.350685 | P14: =IFERROR(SQRT(2*F14*K14/(G14*L14)),0) -> 82.232205 | Q14: =IFERROR(I14/M14,0) -> 68.400646 | R14: =IF(I14<=O14,"Reorder Now",IF(Q14<30,"Monitor","Healthy")) -> Healthy | S14: =RANK(H14,$H$2:$H$21,0) -> 3 | T14: =S14/COUNT($H$2:$H$21) -> 0.15 | U14: =IF(T14<=0.2,"A",IF(T14<=0.5,"B","C")) -> A | V14: =M14*14+N14 -> 50.876712 | W14: =IF(I14<=V14,"Yes","No") -> No | Z14: Monitor | AA14: =COUNTIF($R$2:$R$21,"Monitor") -> 2
A15: ='Sales History'!A15 -> P1013 | B15: ='Sales History'!B15 -> Cooking Oil 1L | C15: ='Sales History'!Q15 -> 129.5 | D15: =_xlfn.FORECAST.LINEAR(13,'Sales History'!D15:O15,{1,2,3,4,5,6,7,8,9,10,11,12}) -> 170.36364 | E15: ='Sales History'!C15 -> Grocery | F15: =C15*12 -> 1554 | G15: =INDEX('Product Master'!$E$2:$E$21,MATCH(A15,'Product Master'!$A$2:$A$21,0)) -> 15.1 | H15: =F15*G15 -> 23465.4 | I15: =INDEX('Product Master'!$G$2:$G$21,MATCH(A15,'Product Master'!$A$2:$A$21,0)) -> 58 | J15: =INDEX('Product Master'!$H$2:$H$21,MATCH(A15,'Product Master'!$A$2:$A$21,0)) -> 21 | K15: =INDEX('Product Master'!$I$2:$I$21,MATCH(A15,'Product Master'!$A$2:$A$21,0)) -> 45.1 | L15: =INDEX('Product Master'!$J$2:$J$21,MATCH(A15,'Product Master'!$A$2:$A$21,0)) -> 0.14 | M15: =F15/365 -> 4.2575342 | N15: =M15*J15*0.2 -> 17.881644 | O15: =M15*J15+N15 -> 107.28986 | P15: =IFERROR(SQRT(2*F15*K15/(G15*L15)),0) -> 257.49944 | Q15: =IFERROR(I15/M15,0) -> 13.622909 | R15: =IF(I15<=O15,"Reorder Now",IF(Q15<30,"Monitor","Healthy")) -> Reorder Now | S15: =RANK(H15,$H$2:$H$21,0) -> 10 | T15: =S15/COUNT($H$2:$H$21) -> 0.5 | U15: =IF(T15<=0.2,"A",IF(T15<=0.5,"B","C")) -> B | V15: =M15*14+N15 -> 77.487123 | W15: =IF(I15<=V15,"Yes","No") -> Yes | Z15: Reorder Now | AA15: =COUNTIF($R$2:$R$21,"Reorder Now") -> 2
A16: ='Sales History'!A16 -> P1014 | B16: ='Sales History'!B16 -> Green Tea Pack | C16: ='Sales History'!Q16 -> 94.583333 | D16: =_xlfn.FORECAST.LINEAR(13,'Sales History'!D16:O16,{1,2,3,4,5,6,7,8,9,10,11,12}) -> 93.060606 | E16: ='Sales History'!C16 -> Beauty & Personal Care | F16: =C16*12 -> 1135 | G16: =INDEX('Product Master'!$E$2:$E$21,MATCH(A16,'Product Master'!$A$2:$A$21,0)) -> 13.36 | H16: =F16*G16 -> 15163.6 | I16: =INDEX('Product Master'!$G$2:$G$21,MATCH(A16,'Product Master'!$A$2:$A$21,0)) -> 176 | J16: =INDEX('Product Master'!$H$2:$H$21,MATCH(A16,'Product Master'!$A$2:$A$21,0)) -> 21 | K16: =INDEX('Product Master'!$I$2:$I$21,MATCH(A16,'Product Master'!$A$2:$A$21,0)) -> 44.97 | L16: =INDEX('Product Master'!$J$2:$J$21,MATCH(A16,'Product Master'!$A$2:$A$21,0)) -> 0.22 | M16: =F16/365 -> 3.109589 | N16: =M16*J16*0.2 -> 13.060274 | O16: =M16*J16+N16 -> 78.361644 | P16: =IFERROR(SQRT(2*F16*K16/(G16*L16)),0) -> 186.36305 | Q16: =IFERROR(I16/M16,0) -> 56.599119 | R16: =IF(I16<=O16,"Reorder Now",IF(Q16<30,"Monitor","Healthy")) -> Healthy | S16: =RANK(H16,$H$2:$H$21,0) -> 13 | T16: =S16/COUNT($H$2:$H$21) -> 0.65 | U16: =IF(T16<=0.2,"A",IF(T16<=0.5,"B","C")) -> C | V16: =M16*14+N16 -> 56.594521 | W16: =IF(I16<=V16,"Yes","No") -> No
A17: ='Sales History'!A17 -> P1015 | B17: ='Sales History'!B17 -> Breakfast Cereal | C17: ='Sales History'!Q17 -> 90.5 | D17: =_xlfn.FORECAST.LINEAR(13,'Sales History'!D17:O17,{1,2,3,4,5,6,7,8,9,10,11,12}) -> 98.863636 | E17: ='Sales History'!C17 -> Electronics Accessories | F17: =C17*12 -> 1086 | G17: =INDEX('Product Master'!$E$2:$E$21,MATCH(A17,'Product Master'!$A$2:$A$21,0)) -> 13.45 | H17: =F17*G17 -> 14606.7 | I17: =INDEX('Product Master'!$G$2:$G$21,MATCH(A17,'Product Master'!$A$2:$A$21,0)) -> 216 | J17: =INDEX('Product Master'!$H$2:$H$21,MATCH(A17,'Product Master'!$A$2:$A$21,0)) -> 5 | K17: =INDEX('Product Master'!$I$2:$I$21,MATCH(A17,'Product Master'!$A$2:$A$21,0)) -> 41.61 | L17: =INDEX('Product Master'!$J$2:$J$21,MATCH(A17,'Product Master'!$A$2:$A$21,0)) -> 0.21 | M17: =F17/365 -> 2.9753425 | N17: =M17*J17*0.2 -> 2.9753425 | O17: =M17*J17+N17 -> 17.852055 | P17: =IFERROR(SQRT(2*F17*K17/(G17*L17)),0) -> 178.87843 | Q17: =IFERROR(I17/M17,0) -> 72.596685 | R17: =IF(I17<=O17,"Reorder Now",IF(Q17<30,"Monitor","Healthy")) -> Healthy | S17: =RANK(H17,$H$2:$H$21,0) -> 14 | T17: =S17/COUNT($H$2:$H$21) -> 0.7 | U17: =IF(T17<=0.2,"A",IF(T17<=0.5,"B","C")) -> C | V17: =M17*14+N17 -> 44.630137 | W17: =IF(I17<=V17,"Yes","No") -> No
A18: ='Sales History'!A18 -> P1016 | B18: ='Sales History'!B18 -> Face Moisturizer | C18: ='Sales History'!Q18 -> 38.75 | D18: =_xlfn.FORECAST.LINEAR(13,'Sales History'!D18:O18,{1,2,3,4,5,6,7,8,9,10,11,12}) -> 41.227273 | E18: ='Sales History'!C18 -> Home & Kitchen | F18: =C18*12 -> 465 | G18: =INDEX('Product Master'!$E$2:$E$21,MATCH(A18,'Product Master'!$A$2:$A$21,0)) -> 20.34 | H18: =F18*G18 -> 9458.1 | I18: =INDEX('Product Master'!$G$2:$G$21,MATCH(A18,'Product Master'!$A$2:$A$21,0)) -> 284 | J18: =INDEX('Product Master'!$H$2:$H$21,MATCH(A18,'Product Master'!$A$2:$A$21,0)) -> 5 | K18: =INDEX('Product Master'!$I$2:$I$21,MATCH(A18,'Product Master'!$A$2:$A$21,0)) -> 27.36 | L18: =INDEX('Product Master'!$J$2:$J$21,MATCH(A18,'Product Master'!$A$2:$A$21,0)) -> 0.15 | M18: =F18/365 -> 1.2739726 | N18: =M18*J18*0.2 -> 1.2739726 | O18: =M18*J18+N18 -> 7.6438356 | P18: =IFERROR(SQRT(2*F18*K18/(G18*L18)),0) -> 91.322631 | Q18: =IFERROR(I18/M18,0) -> 222.92473 | R18: =IF(I18<=O18,"Reorder Now",IF(Q18<30,"Monitor","Healthy")) -> Healthy | S18: =RANK(H18,$H$2:$H$21,0) -> 16 | T18: =S18/COUNT($H$2:$H$21) -> 0.8 | U18: =IF(T18<=0.2,"A",IF(T18<=0.5,"B","C")) -> C | V18: =M18*14+N18 -> 19.109589 | W18: =IF(I18<=V18,"Yes","No") -> No
A19: ='Sales History'!A19 -> P1017 | B19: ='Sales History'!B19 -> Shampoo 400ml | C19: ='Sales History'!Q19 -> 127.58333 | D19: =_xlfn.FORECAST.LINEAR(13,'Sales History'!D19:O19,{1,2,3,4,5,6,7,8,9,10,11,12}) -> 171.78788 | E19: ='Sales History'!C19 -> Apparel | F19: =C19*12 -> 1531 | G19: =INDEX('Product Master'!$E$2:$E$21,MATCH(A19,'Product Master'!$A$2:$A$21,0)) -> 32.91 | H19: =F19*G19 -> 50385.21 | I19: =INDEX('Product Master'!$G$2:$G$21,MATCH(A19,'Product Master'!$A$2:$A$21,0)) -> 365 | J19: =INDEX('Product Master'!$H$2:$H$21,MATCH(A19,'Product Master'!$A$2:$A$21,0)) -> 5 | K19: =INDEX('Product Master'!$I$2:$I$21,MATCH(A19,'Product Master'!$A$2:$A$21,0)) -> 40.26 | L19: =INDEX('Product Master'!$J$2:$J$21,MATCH(A19,'Product Master'!$A$2:$A$21,0)) -> 0.27 | M19: =F19/365 -> 4.1945205 | N19: =M19*J19*0.2 -> 4.1945205 | O19: =M19*J19+N19 -> 25.167123 | P19: =IFERROR(SQRT(2*F19*K19/(G19*L19)),0) -> 117.786 | Q19: =IFERROR(I19/M19,0) -> 87.018289 | R19: =IF(I19<=O19,"Reorder Now",IF(Q19<30,"Monitor","Healthy")) -> Healthy | S19: =RANK(H19,$H$2:$H$21,0) -> 5 | T19: =S19/COUNT($H$2:$H$21) -> 0.25 | U19: =IF(T19<=0.2,"A",IF(T19<=0.5,"B","C")) -> B | V19: =M19*14+N19 -> 62.917808 | W19: =IF(I19<=V19,"Yes","No") -> No
A20: ='Sales History'!A20 -> P1018 | B20: ='Sales History'!B20 -> Hand Wash 250ml | C20: ='Sales History'!Q20 -> 127.25 | D20: =_xlfn.FORECAST.LINEAR(13,'Sales History'!D20:O20,{1,2,3,4,5,6,7,8,9,10,11,12}) -> 171.45455 | E20: ='Sales History'!C20 -> Grocery | F20: =C20*12 -> 1527 | G20: =INDEX('Product Master'!$E$2:$E$21,MATCH(A20,'Product Master'!$A$2:$A$21,0)) -> 27.62 | H20: =F20*G20 -> 42175.74 | I20: =INDEX('Product Master'!$G$2:$G$21,MATCH(A20,'Product Master'!$A$2:$A$21,0)) -> 318 | J20: =INDEX('Product Master'!$H$2:$H$21,MATCH(A20,'Product Master'!$A$2:$A$21,0)) -> 5 | K20: =INDEX('Product Master'!$I$2:$I$21,MATCH(A20,'Product Master'!$A$2:$A$21,0)) -> 32.23 | L20: =INDEX('Product Master'!$J$2:$J$21,MATCH(A20,'Product Master'!$A$2:$A$21,0)) -> 0.22 | M20: =F20/365 -> 4.1835616 | N20: =M20*J20*0.2 -> 4.1835616 | O20: =M20*J20+N20 -> 25.10137 | P20: =IFERROR(SQRT(2*F20*K20/(G20*L20)),0) -> 127.27453 | Q20: =IFERROR(I20/M20,0) -> 76.011788 | R20: =IF(I20<=O20,"Reorder Now",IF(Q20<30,"Monitor","Healthy")) -> Healthy | S20: =RANK(H20,$H$2:$H$21,0) -> 7 | T20: =S20/COUNT($H$2:$H$21) -> 0.35 | U20: =IF(T20<=0.2,"A",IF(T20<=0.5,"B","C")) -> B | V20: =M20*14+N20 -> 62.753425 | W20: =IF(I20<=V20,"Yes","No") -> No
A21: ='Sales History'!A21 -> P1019 | B21: ='Sales History'!B21 -> Lip Balm Pack | C21: ='Sales History'!Q21 -> 37.916667 | D21: =_xlfn.FORECAST.LINEAR(13,'Sales History'!D21:O21,{1,2,3,4,5,6,7,8,9,10,11,12}) -> 25.666667 | E21: ='Sales History'!C21 -> Beauty & Personal Care | F21: =C21*12 -> 455 | G21: =INDEX('Product Master'!$E$2:$E$21,MATCH(A21,'Product Master'!$A$2:$A$21,0)) -> 19.6 | H21: =F21*G21 -> 8918 | I21: =INDEX('Product Master'!$G$2:$G$21,MATCH(A21,'Product Master'!$A$2:$A$21,0)) -> 285 | J21: =INDEX('Product Master'!$H$2:$H$21,MATCH(A21,'Product Master'!$A$2:$A$21,0)) -> 14 | K21: =INDEX('Product Master'!$I$2:$I$21,MATCH(A21,'Product Master'!$A$2:$A$21,0)) -> 58.73 | L21: =INDEX('Product Master'!$J$2:$J$21,MATCH(A21,'Product Master'!$A$2:$A$21,0)) -> 0.23 | M21: =F21/365 -> 1.2465753 | N21: =M21*J21*0.2 -> 3.490411 | O21: =M21*J21+N21 -> 20.942466 | P21: =IFERROR(SQRT(2*F21*K21/(G21*L21)),0) -> 108.88267 | Q21: =IFERROR(I21/M21,0) -> 228.62637 | R21: =IF(I21<=O21,"Reorder Now",IF(Q21<30,"Monitor","Healthy")) -> Healthy | S21: =RANK(H21,$H$2:$H$21,0) -> 17 | T21: =S21/COUNT($H$2:$H$21) -> 0.85 | U21: =IF(T21<=0.2,"A",IF(T21<=0.5,"B","C")) -> C | V21: =M21*14+N21 -> 20.942466 | W21: =IF(I21<=V21,"Yes","No") -> No
